forge_flow/__init__.py
forge_flow/exceptions.py
forge_flow/py.typed
forge_flow/features/__init__.py
forge_flow/features/cleaner.py
forge_flow/features/engineer.py
forge_flow/features/pipeline.py
forge_flow/features/quality_gate.py
forge_flow/ingestion/__init__.py
forge_flow/ingestion/api_connector.py
forge_flow/ingestion/base.py
forge_flow/ingestion/db_connector.py
forge_flow/ingestion/file_connector.py
forge_flow/observability/__init__.py
forge_flow/observability/drift_detector.py
forge_flow/schemas/__init__.py
forge_flow/schemas/base.py
forge_flow/schemas/validator.py
forge_flow/serving/__init__.py
forge_flow/serving/online_store.py
forge_flow-0.1.0.dist-info/METADATA
forge_flow-0.1.0.dist-info/WHEEL
forge_flow-0.1.0.dist-info/top_level.txt
forge_flow-0.1.0.dist-info/RECORD
