Metadata-Version: 2.4
Name: forge-flow
Version: 0.1.0
Summary: Engineering-First ML Library for building robust, production-grade machine learning pipelines
Author: ForgeFlow Contributors
License: MIT
Project-URL: Homepage, https://github.com/your-org/forge-flow
Project-URL: Documentation, https://forge-flow.readthedocs.io
Project-URL: Repository, https://github.com/your-org/forge-flow
Project-URL: Issues, https://github.com/your-org/forge-flow/issues
Keywords: machine-learning,mlops,feature-store,data-validation,ml-pipeline
Classifier: Development Status :: 3 - Alpha
Classifier: Intended Audience :: Developers
Classifier: License :: OSI Approved :: MIT License
Classifier: Programming Language :: Python :: 3
Classifier: Programming Language :: Python :: 3.10
Classifier: Programming Language :: Python :: 3.11
Classifier: Programming Language :: Python :: 3.12
Classifier: Topic :: Scientific/Engineering :: Artificial Intelligence
Classifier: Topic :: Software Development :: Libraries :: Python Modules
Requires-Python: >=3.10
Requires-Dist: pandas>=2.0.0
Requires-Dist: numpy>=1.24.0
Requires-Dist: pydantic>=2.0.0
Requires-Dist: pyarrow>=12.0.0
Requires-Dist: requests>=2.31.0
Requires-Dist: structlog>=23.0.0
Requires-Dist: fsspec>=2023.1.0
Requires-Dist: tenacity>=8.2.0
Requires-Dist: scipy>=1.11.0
Requires-Dist: scikit-learn>=1.3.0
Provides-Extra: dev
Requires-Dist: pytest>=7.4.0; extra == "dev"
Requires-Dist: pytest-cov>=4.1.0; extra == "dev"
Requires-Dist: pytest-mock>=3.11.0; extra == "dev"
Requires-Dist: black>=23.12.0; extra == "dev"
Requires-Dist: ruff>=0.1.9; extra == "dev"
Requires-Dist: mypy>=1.8.0; extra == "dev"
Requires-Dist: pre-commit>=3.5.0; extra == "dev"
Requires-Dist: pandas-stubs>=2.0.0; extra == "dev"
Requires-Dist: types-requests>=2.31.0; extra == "dev"
Provides-Extra: serving
Requires-Dist: redis>=5.0.0; extra == "serving"
Requires-Dist: fastapi>=0.104.0; extra == "serving"
Requires-Dist: uvicorn>=0.24.0; extra == "serving"
Provides-Extra: database
Requires-Dist: sqlalchemy>=2.0.0; extra == "database"
Requires-Dist: psycopg2-binary>=2.9.0; extra == "database"
Provides-Extra: all
Requires-Dist: forge-flow[database,dev,serving]; extra == "all"
